learner_pathway_progress/__init__.py
learner_pathway_progress/admin.py
learner_pathway_progress/apps.py
learner_pathway_progress/constants.py
learner_pathway_progress/models.py
learner_pathway_progress/signals.py
learner_pathway_progress/utilities.py
learner_pathway_progress/waffle.py
learner_pathway_progress/api/__init__.py
learner_pathway_progress/api/filters.py
learner_pathway_progress/api/serializers.py
learner_pathway_progress/api/urls.py
learner_pathway_progress/api/v1/__init__.py
learner_pathway_progress/api/v1/urls.py
learner_pathway_progress/api/v1/views.py
learner_pathway_progress/management/__init__.py
learner_pathway_progress/management/commands/__init__.py
learner_pathway_progress/management/commands/update_all_pathways_progress.py
learner_pathway_progress/management/commands/update_existing_pathways_progress.py
learner_pathway_progress/management/tests/__init__.py
learner_pathway_progress/management/tests/test_update_all_pathways_progress.py
learner_pathway_progress/management/tests/test_update_existing_pathways_progress.py
learner_pathway_progress/migrations/0001_initial.py
learner_pathway_progress/migrations/0002_historicallearnerpathwayprogress_learnerpathwayprogress.py
learner_pathway_progress/migrations/0003_auto_20220901_0616.py
learner_pathway_progress/migrations/0004_auto_20220907_0316.py
learner_pathway_progress/migrations/0005_auto_20221007_0758.py
learner_pathway_progress/migrations/__init__.py
learner_pathway_progress/templates/learner_pathway_progress/base.html
learner_pathway_progress-1.3.4.dist-info/LICENSE.txt
learner_pathway_progress-1.3.4.dist-info/METADATA
learner_pathway_progress-1.3.4.dist-info/WHEEL
learner_pathway_progress-1.3.4.dist-info/entry_points.txt
learner_pathway_progress-1.3.4.dist-info/top_level.txt
learner_pathway_progress-1.3.4.dist-info/RECORD
