Metadata-Version: 2.1
Name: learner-pathway-progress
Version: 1.3.4
Summary: A plugin to track learners progress in pathways.
Home-page: https://github.com/edx/learner-pathway-progress
Author: edX
Author-email: oscm@edx.org
License: AGPL 3.0
Keywords: Python edx
Platform: UNKNOWN
Classifier: Development Status :: 3 - Alpha
Classifier: Framework :: Django
Classifier: Framework :: Django :: 2.2
Classifier: Intended Audience :: Developers
Classifier: License :: OSI Approved :: GNU Affero General Public License v3 or later (AGPLv3+)
Classifier: Natural Language :: English
Classifier: Programming Language :: Python :: 3
Classifier: Programming Language :: Python :: 3.8
Requires-Python: >=3.8
Requires-Dist: Django
Requires-Dist: django-filter
Requires-Dist: django-model-utils
Requires-Dist: django-simple-history
Requires-Dist: djangorestframework
Requires-Dist: edx-django-utils
Requires-Dist: edx-drf-extensions
Requires-Dist: edx-enterprise
Requires-Dist: edx-opaque-keys
Requires-Dist: edx-toggles (>=1.2.0)
Requires-Dist: jsonfield
Requires-Dist: pytz
Requires-Dist: requests
